domain_event_pattern/__init__.py
domain_event_pattern/py.typed
domain_event_pattern/buses/__init__.py
domain_event_pattern/buses/event_bus.py
domain_event_pattern/errors/__init__.py
domain_event_pattern/errors/domain_event_pattern_base_error.py
domain_event_pattern/errors/handler_error.py
domain_event_pattern/errors/publication_error.py
domain_event_pattern/models/__init__.py
domain_event_pattern/models/domain_event.py
domain_event_pattern/models/domain_event_aggregate_identifier.py
domain_event_pattern/models/domain_event_identifier.py
domain_event_pattern/models/domain_event_name.py
domain_event_pattern/models/domain_event_occurred_datetime.py
domain_event_pattern/models/domain_event_subscriber.py
domain_event_pattern/models/domain_event_subscriber_name.py
domain_event_pattern/models/testing/__init__.py
domain_event_pattern/models/testing/mothers/__init__.py
domain_event_pattern/models/testing/mothers/domain_event_identifier_mother.py
domain_event_pattern/models/testing/mothers/domain_event_name_mother.py
domain_event_pattern/models/testing/mothers/domain_event_occurred_datetime_mother.py
domain_event_pattern-0.7.0.dist-info/METADATA
domain_event_pattern-0.7.0.dist-info/WHEEL
domain_event_pattern-0.7.0.dist-info/licenses/LICENSE.md
domain_event_pattern-0.7.0.dist-info/RECORD
