Metadata-Version: 2.4
Name: domain-event-pattern
Version: 0.7.0
Summary: The Domain Event Pattern is a Python package that implements the Domain Event pattern.
Project-URL: Homepage, https://github.com/adriamontoto/domain-event-pattern
Project-URL: Repository, https://github.com/adriamontoto/domain-event-pattern
Project-URL: Issues, https://github.com/adriamontoto/domain-event-pattern/issues
Author: Adria Montoto
License-Expression: MIT
License-File: LICENSE.md
Keywords: development,domain-events,event-bus,python,tools,utilities
Classifier: Intended Audience :: Developers
Classifier: License :: OSI Approved :: MIT License
Classifier: Operating System :: OS Independent
Classifier: Programming Language :: Python
Classifier: Programming Language :: Python :: 3
Classifier: Programming Language :: Python :: 3.11
Classifier: Programming Language :: Python :: 3.12
Classifier: Programming Language :: Python :: 3.13
Classifier: Typing :: Typed
Requires-Python: >=3.11
Requires-Dist: value-object-pattern>=1.14.1
